validateCodeTool/NotoSansCJK-DemiLight.ttc
validateCodeTool/__init__.py
validateCodeTool/validate_code.py
validateCodeTool-1.0.0.dist-info/DESCRIPTION.rst
validateCodeTool-1.0.0.dist-info/METADATA
validateCodeTool-1.0.0.dist-info/RECORD
validateCodeTool-1.0.0.dist-info/WHEEL
validateCodeTool-1.0.0.dist-info/metadata.json
validateCodeTool-1.0.0.dist-info/top_level.txt
