Metadata-Version: 2.0
Name: validateCodeTool
Version: 1.0.0
Summary: a simple library  to help you to generate authentication code. It's useful and flexible and convenient.
Home-page: https://github.com/Andrewpqc/authentication_code_generator
Author: andrewpqc
Author-email: andrewpqc@mails.ccnu.edu.cn
License: UNKNOWN
Keywords: convenient flexible development
Platform: UNKNOWN
Requires-Dist: Pillow (>=4.2.1)
